Metadata-Version: 2.0
Name: pinax-notifications-no-scoping
Version: 4.0.3
Summary: User notification management for the Django web framework
Home-page: http://pinax-notifications.rtfd.org/
Author: Pinax Developers
Author-email: developers@pinaxprojects.com
License: MIT
Platform: UNKNOWN
Classifier: Development Status :: 5 - Production/Stable
Classifier: Environment :: Web Environment
Classifier: Framework :: Django
Classifier: Intended Audience :: Developers
Classifier: License :: OSI Approved :: MIT License
Classifier: Operating System :: OS Independent
Classifier: Programming Language :: Python
Classifier: Programming Language :: Python :: 2
Classifier: Programming Language :: Python :: 3
Classifier: Topic :: Software Development :: Libraries :: Python Modules
Requires-Dist: django-appconf (>=1.0.1)
